odoo/addons/sale_stock_line_sequence/README.rst
odoo/addons/sale_stock_line_sequence/__init__.py
odoo/addons/sale_stock_line_sequence/__manifest__.py
odoo/addons/sale_stock_line_sequence/i18n/sale_stock_line_sequence.pot
odoo/addons/sale_stock_line_sequence/models/__init__.py
odoo/addons/sale_stock_line_sequence/models/sale_order.py
odoo/addons/sale_stock_line_sequence/readme/CONTRIBUTORS.rst
odoo/addons/sale_stock_line_sequence/readme/DESCRIPTION.rst
odoo/addons/sale_stock_line_sequence/static/description/icon.png
odoo/addons/sale_stock_line_sequence/static/description/index.html
odoo/addons/sale_stock_line_sequence/tests/__init__.py
odoo/addons/sale_stock_line_sequence/tests/test_line_sequence.py
odoo13_addon_sale_stock_line_sequence-13.0.1.0.1.dev4.dist-info/METADATA
odoo13_addon_sale_stock_line_sequence-13.0.1.0.1.dev4.dist-info/WHEEL
odoo13_addon_sale_stock_line_sequence-13.0.1.0.1.dev4.dist-info/top_level.txt
odoo13_addon_sale_stock_line_sequence-13.0.1.0.1.dev4.dist-info/RECORD
